Workbook
Name Slicer_Category: #N/A
Name Slicer_Region: #N/A

Sheet Instruction
B1: Dataset: Superstore Dataset
B7: Steps Performed: 1. Imported dataset into Excel 2. Cleaned data (removed duplicates, formatted columns) 3. Created Pivot Tables for analysis 4. Applied formulas (SUM, AVERAGE, VLOOKUP, INDEX-MATCH, IF) 5. Created charts for visualization 6. Developed interactive dashboard using slicers and timeline
B22: Tools Used: Microsoft Excel, Pivot Tables, Charts, Formulas
B26: Conclusion: The dashboard provides insights into sales performance by category, region and time.

Sheet Report
B2: Sales Performance Analysis Report
B6: This project analyzes retail sales data to understand business performance using Excel tools such as Pivot Tables, Charts, and an Interactive Dashboard.The goal is to identify trends, regional performance, and category-wise sales insights.
B12: Key Insights: • Technology category has the highest sales performance. • West region generates maximum profit compared to others. • Sales trend shows variation across years indicating demand changes. • A small number of orders contribute significantly to total revenue.
B21: Dashboard Features: • Interactive slicers for Category and Region • KPI indicators (Total Sales, Profit, Average Sales, Orders) • Visual charts for easy data interpretation
B30: Conclusion: The dashboard provides clear insights into business performance. It helps identify strong and weak regions, improve decision-making, and supports data-driven business strategies for growth.

Sheet DashBoard
A1: Sales Performance Dashboard

Sheet Analysis
B1: Calculation Sheet | V1: What If Analysis
R2: Top 10 Products by Sales
B5: Total Sales | D5: =SUM(CleanData!R:R) -> 129357.02 | H5: Profit Margin | J5: =SUM(CleanData!U:U)/SUM(CleanData!R:R) -> 0.041286064 | R5: Row Labels | S5: Sum of Sales | V5: Goal Seek | AB5: Scenario Manager
R6: Lexmark MX611dhe Monochrome Laser Printer | S6: 11219.934
R7: Riverside Palais Royal Lawyers Bookcase, Royale Cherry Finish | S7: 5479.6956
B8: Total Profit | D8: =SUM(CleanData!U:U) -> 5340.642 | H8: Vlookup | J8: =VLOOKUP(O8, CleanData!B:Z, 17, FALSE) -> 665.88 | M8: Order ID | O8: CA-2014-105893 | R8: GBC DocuBind P400 Electric Binding System | S8: 4355.168 | W8: Quantity | X8: 25 | AC8: Quantity | AD8: 10
R9: Canon imageCLASS MF7460 Monochrome Digital Laser Multifunction Copier | S9: 3991.98 | W9: Unit Price | X9: 200 | AC9: Unit Price | AD9: 500
R10: Logitech P710e Mobile Speakerphone | S10: 3965.346 | W10: Revenue | X10: =X8*X9 -> 5000 | AC10: Revenue | AD10: =AD8*AD9 -> 5000
B11: Average Sales | D11: =AVERAGE(CleanData!R2:R500) -> 259.2325 | H11: index+match | J11: =INDEX(CleanData!E:E, MATCH(O8, CleanData!B:B, 0)) -> Standard Class | R11: Global Deluxe High-Back Manager's Chair | S11: 3059.986
R12: Apple iPhone 5S | S12: 2735.952
R13: Hon Deluxe Fabric Upholstered Stacking Chairs, Rounded Back | S13: 2683.78
B14: Total Orders | D14: =COUNTA(CleanData!B:B) -> 500 | H14: if condition | J14: =IF(CleanData!R:R>500,"High","Low") -> Low | R14: Xerox WorkCentre 6505DN Laser Multifunction Printer | S14: 2519.958
R15: Atlantic Metals Mobile 3-Shelf Bookcases, Custom Colors | S15: 2202.6712
R16: Grand Total | S16: 42214.471
B18: Filtered Data (Westy Region - Technology)
B23: 8 | C23: CA-2014-115812 | D23: 41799 | E23: 41804 | F23: Standard Class | G23: BH-11710 | H23: Brosina Hoffman | I23: Consumer | J23: United States | K23: Los Angeles | L23: California | M23: 90032 | N23: West | O23: TEC-PH-10002275 | P23: Technology | Q23: Phones | R23: Mitel 5320 IP Phone VoIP phone | S23: 907.152 | T23: 6 | U23: 0.2 | V23: 90.7152 | W23: High | X23: 46152.606
B24: 12 | C24: CA-2014-115812 | D24: 41799 | E24: 41804 | F24: Standard Class | G24: BH-11710 | H24: Brosina Hoffman | I24: Consumer | J24: United States | K24: Los Angeles | L24: California | M24: 90032 | N24: West | O24: TEC-PH-10002033 | P24: Technology | Q24: Phones | R24: Konftel 250 Conference phone - Charcoal black | S24: 911.424 | T24: 4 | U24: 0.2 | V24: 68.3568 | W24: High | X24: 46152.606
B25: 20 | C25: CA-2014-143336 | D25: 41878 | E25: 41883 | F25: Second Class | G25: ZD-21925 | H25: Zuschuss Donatelli | I25: Consumer | J25: United States | K25: San Francisco | L25: California | M25: 94109 | N25: West | O25: TEC-PH-10001949 | P25: Technology | Q25: Phones | R25: Cisco SPA 501G IP Phone | S25: 213.48 | T25: 3 | U25: 0.2 | V25: 16.011 | W25: Low | X25: 46152.606
B26: 27 | C26: CA-2016-121755 | D26: 42385 | E26: 42389 | F26: Second Class | G26: EH-13945 | H26: Eric Hoffmann | I26: Consumer | J26: United States | K26: Los Angeles | L26: California | M26: 90049 | N26: West | O26: TEC-AC-10003027 | P26: Technology | Q26: Accessories | R26: Imation 8GB Mini TravelDrive USB 2.0 Flash Drive | S26: 90.57 | T26: 3 | U26: 0 | V26: 11.7741 | W26: Low | X26: 46152.606
B27: 63 | C27: CA-2015-135545 | D27: 42332 | E27: 42338 | F27: Standard Class | G27: KM-16720 | H27: Kunst Miller | I27: Consumer | J27: United States | K27: Los Angeles | L27: California | M27: 90004 | N27: West | O27: TEC-AC-10004633 | P27: Technology | Q27: Accessories | R27: Verbatim 25 GB 6x Blu-ray Single Layer Recordable Disc, 3/Pack | S27: 13.98 | T27: 2 | U27: 0 | V27: 6.1512 | W27: Low | X27: 46152.606
B28: 69 | C28: CA-2014-106376 | D28: 41978 | E28: 41983 | F28: Standard Class | G28: BS-11590 | H28: Brendan Sweed | I28: Corporate | J28: United States | K28: Gilbert | L28: Arizona | M28: 85234 | N28: West | O28: TEC-PH-10002726 | P28: Technology | Q28: Phones | R28: netTALK DUO VoIP Telephone Service | S28: 167.968 | T28: 4 | U28: 0.2 | V28: 62.988 | W28: Low | X28: 46152.606
B29: 91 | C29: CA-2016-109806 | D29: 42630 | E29: 42635 | F29: Standard Class | G29: JS-15685 | H29: Jim Sink | I29: Corporate | J29: United States | K29: Los Angeles | L29: California | M29: 90036 | N29: West | O29: TEC-PH-10004093 | P29: Technology | Q29: Phones | R29: Panasonic Kx-TS550 | S29: 73.584 | T29: 2 | U29: 0.2 | V29: 8.2782 | W29: Low | X29: 46152.606
B30: 104 | C30: US-2015-156867 | D30: 42321 | E30: 42325 | F30: Standard Class | G30: LC-16870 | H30: Lena Cacioppo | I30: Consumer | J30: United States | K30: Aurora | L30: Colorado | M30: 80013 | N30: West | O30: TEC-AC-10001552 | P30: Technology | Q30: Accessories | R30: Logitech K350 2.4Ghz Wireless Keyboard | S30: 238.896 | T30: 6 | U30: 0.2 | V30: -26.8758 | W30: Low | X30: 46152.606
B31: 153 | C31: CA-2016-158834 | D31: 42442 | E31: 42445 | F31: First Class | G31: TW-21025 | H31: Tamara Willingham | I31: Home Office | J31: United States | K31: Scottsdale | L31: Arizona | M31: 85254 | N31: West | O31: TEC-PH-10001254 | P31: Technology | Q31: Phones | R31: Jabra BIZ 2300 Duo QD Duo Corded Headset | S31: 203.184 | T31: 2 | U31: 0.2 | V31: 15.2388 | W31: Low | X31: 46152.606
B32: 187 | C32: CA-2014-123260 | D32: 41877 | E32: 41881 | F32: Standard Class | G32: FM-14290 | H32: Frank Merwin | I32: Home Office | J32: United States | K32: Los Angeles | L32: California | M32: 90032 | N32: West | O32: TEC-AC-10002323 | P32: Technology | Q32: Accessories | R32: SanDisk Ultra 32 GB MicroSDHC Class 10 Memory Card | S32: 176.8 | T32: 8 | U32: 0 | V32: 22.984 | W32: Low | X32: 46152.606
B33: 206 | C33: CA-2017-108329 | D33: 43078 | E33: 43083 | F33: Standard Class | G33: LE-16810 | H33: Laurel Elliston | I33: Consumer | J33: United States | K33: Whittier | L33: California | M33: 90604 | N33: West | O33: TEC-PH-10001918 | P33: Technology | Q33: Phones | R33: Nortel Business Series Terminal T7208 Digital phone | S33: 444.768 | T33: 4 | U33: 0.2 | V33: 44.4768 | W33: Low | X33: 46152.606
B34: 219 | C34: CA-2016-130162 | D34: 42671 | E34: 42675 | F34: Standard Class | G34: JH-15910 | H34: Jonathan Howell | I34: Consumer | J34: United States | K34: Los Angeles | L34: California | M34: 90032 | N34: West | O34: TEC-PH-10002563 | P34: Technology | Q34: Phones | R34: Adtran 1202752G1 | S34: 302.376 | T34: 3 | U34: 0.2 | V34: 22.6782 | W34: Low | X34: 46152.606
... B54: 494 | C54: CA-2016-169166 | D54: 42499 | E54: 42504 | F54: Standard Class | G54: SS-20590 | H54: Sonia Sunley | I54: Consumer | J54: United States | K54: Seattle | L54: Washington | M54: 98115 | N54: West | O54: TEC-AC-10000991 | P54: Technology | Q54: Phones | R54: Sony Micro Vault Click 8 GB USB 2.0 Flash Drive | S54: 93.98 | T54: 2 | U54: 0 | V54: 13.1572 | W54: Low | X54: 46152.606

Sheet PivotTable
B3: Sales By Category | E3: Profit By Region | H3: Sales Trend
B6: Row Labels | C6: Sum of Sales | E6: Row Labels | F6: Sum of Profit | H6: Row Labels | I6: Sum of Sales
B7: Technology | C7: 9345.558 | E7: East | F7: 959.4564 | H7: 2014 | I7: 4929.818
B8: Grand Total | C8: 9345.558 | E8: Grand Total | F8: 959.4564 | H8: 2015 | I8: 2429.038
H9: 2016 | I9: 1866.382
H10: 2017 | I10: 120.32
H11: Grand Total | I11: 9345.558

Sheet Scenario Summary
B2: Scenario Summary
D3: Current Values: | E3: Low Sale | F3: High Sale
E4: Created by Admin on 5/10/2026 | F4: Created by Admin on 5/10/2026
B5: Changing Cells:
C6: $AD$8 | D6: 10 | E6: 5 | F6: 20
C7: $AD$9 | D7: 500 | E7: 200 | F7: 500
B8: Result Cells:
C9: $AD$10 | D9: 5000 | E9: 1000 | F9: 10000
B10: Notes: Current Values column represents values of changing cells at
B11: time Scenario Summary Report was created. Changing cells for each
B12: scenario are highlighted in gray.

Sheet Linear Regression
A1: SUMMARY OUTPUT
A3: Regression Statistics
A4: Multiple R | B4: 0.26623925
A5: R Square | B5: 0.070883336
A6: Adjusted R Square | B6: 0.069013886
A7: Standard Error | B7: 590.34086
A8: Observations | B8: 499
A10: ANOVA
B11: df | C11: SS | D11: MS | E11: F | F11: Significance F
A12: Regression | B12: 1 | C12: 13214051 | D12: 13214051 | E12: 37.916679 | F12: 1.5239985e-09
A13: Residual | B13: 497 | C13: 1.7320566e+08 | D13: 348502.34
A14: Total | B14: 498 | C14: 1.8641971e+08
B16: Coefficients | C16: Standard Error | D16: t Stat | E16: P-value | F16: Lower 95% | G16: Upper 95% | H16: Lower 95.0% | I16: Upper 95.0%
A17: Intercept | B17: -15.606566 | C17: 51.870729 | D17: -0.30087423 | E17: 0.76363623 | F17: -117.51951 | G17: 86.306378 | H17: -117.51951 | I17: 86.306378
A18: X Variable 1 | B18: 69.829273 | C18: 11.340243 | D18: 6.157652 | E18: 1.5239985e-09 | F18: 47.548546 | G18: 92.110001 | H18: 47.548546 | I18: 92.110001
A20: Regression shows a positive relationship between Quantity and Sales, but the impact is weak as R² is low.

Sheet CleanData
A1: Row ID | B1: Order ID | C1: Order Date | D1: Ship Date | E1: Ship Mode | F1: Customer ID | G1: Customer Name | H1: Segment | I1: Country | J1: City | K1: State | L1: Postal Code | M1: Region | N1: Product ID | O1: Category | P1: Sub-Category | Q1: Product Name | R1: Sales | S1: Quantity | T1: Discount | U1: Profit | V1: Sales Level | W1: TimeStamp | X1: Days to Ship | Y1: Current Year | Z1: End of month | AA1: Customer short name
A2: 1 | B2: CA-2016-152156 | C2: 42682 | D2: 42685 | E2: Second Class | F2: CG-12520 | G2: Claire Gute | H2: Consumer | I2: United States | J2: Henderson | K2: Kentucky | L2: 42420 | M2: South | N2: FUR-BO-10001798 | O2: Furniture | P2: Bookcases | Q2: Bush Somerset Collection Bookcase | R2: 261.96 | S2: 2 | T2: 0 | U2: 41.9136 | V2: =IF(data[[#This Row],[Sales]]>500,"High","Low") -> Low | W2: =NOW() -> 46152.637 | X2: =DATEDIF(data[[#This Row],[Order Date]], data[[#This Row],[Ship Date]], "d") -> 3 | Y2: =YEAR(TODAY()) -> 2026 | Z2: =EOMONTH(data[[#This Row],[Order Date]],0) -> 42704 | AA2: =LEFT(data[[#This Row],[Customer Name]],3) -> Cla
A3: 2 | B3: CA-2016-152156 | C3: 42682 | D3: 42685 | E3: Second Class | F3: CG-12520 | G3: Claire Gute | H3: Consumer | I3: United States | J3: Henderson | K3: Kentucky | L3: 42420 | M3: South | N3: FUR-CH-10000454 | O3: Furniture | P3: Chairs | Q3: Hon Deluxe Fabric Upholstered Stacking Chairs, Rounded Back | R3: 731.94 | S3: 3 | T3: 0 | U3: 219.582 | V3: =IF(data[[#This Row],[Sales]]>500,"High","Low") -> High | W3: =NOW() -> 46152.637 | X3: =DATEDIF(data[[#This Row],[Order Date]], data[[#This Row],[Ship Date]], "d") -> 3 | Y3: =YEAR(TODAY()) -> 2026 | Z3: =EOMONTH(data[[#This Row],[Order Date]],0) -> 42704 | AA3: =LEFT(data[[#This Row],[Customer Name]],3) -> Cla
A4: 3 | B4: CA-2016-138688 | C4: 42533 | D4: 42537 | E4: Second Class | F4: DV-13045 | G4: Darrin Van Huff | H4: Corporate | I4: United States | J4: Los Angeles | K4: California | L4: 90036 | M4: West | N4: OFF-LA-10000240 | O4: Office Supplies | P4: Labels | Q4: Self-Adhesive Address Labels for Typewriters by Universal | R4: 14.62 | S4: 2 | T4: 0 | U4: 6.8714 | V4: =IF(data[[#This Row],[Sales]]>500,"High","Low") -> Low | W4: =NOW() -> 46152.637 | X4: =DATEDIF(data[[#This Row],[Order Date]], data[[#This Row],[Ship Date]], "d") -> 4 | Y4: =YEAR(TODAY()) -> 2026 | Z4: =EOMONTH(data[[#This Row],[Order Date]],0) -> 42551 | AA4: =LEFT(data[[#This Row],[Customer Name]],3) -> Dar
A5: 4 | B5: US-2015-108966 | C5: 42288 | D5: 42295 | E5: Standard Class | F5: SO-20335 | G5: Sean O'Donnell | H5: Consumer | I5: United States | J5: Fort Lauderdale | K5: Florida | L5: 33311 | M5: South | N5: FUR-TA-10000577 | O5: Furniture | P5: Tables | Q5: Bretford CR4500 Series Slim Rectangular Table | R5: 957.5775 | S5: 5 | T5: 0.45 | U5: -383.031 | V5: =IF(data[[#This Row],[Sales]]>500,"High","Low") -> High | W5: =NOW() -> 46152.637 | X5: =DATEDIF(data[[#This Row],[Order Date]], data[[#This Row],[Ship Date]], "d") -> 7 | Y5: =YEAR(TODAY()) -> 2026 | Z5: =EOMONTH(data[[#This Row],[Order Date]],0) -> 42308 | AA5: =LEFT(data[[#This Row],[Customer Name]],3) -> Sea
A6: 5 | B6: US-2015-108966 | C6: 42288 | D6: 42295 | E6: Standard Class | F6: SO-20335 | G6: Sean O'Donnell | H6: Consumer | I6: United States | J6: Fort Lauderdale | K6: Florida | L6: 33311 | M6: South | N6: OFF-ST-10000760 | O6: Office Supplies | P6: Storage | Q6: Eldon Fold 'N Roll Cart System | R6: 22.368 | S6: 2 | T6: 0.2 | U6: 2.5164 | V6: =IF(data[[#This Row],[Sales]]>500,"High","Low") -> Low | W6: =NOW() -> 46152.637 | X6: =DATEDIF(data[[#This Row],[Order Date]], data[[#This Row],[Ship Date]], "d") -> 7 | Y6: =YEAR(TODAY()) -> 2026 | Z6: =EOMONTH(data[[#This Row],[Order Date]],0) -> 42308 | AA6: =LEFT(data[[#This Row],[Customer Name]],3) -> Sea
A7: 6 | B7: CA-2014-115812 | C7: 41799 | D7: 41804 | E7: Standard Class | F7: BH-11710 | G7: Brosina Hoffman | H7: Consumer | I7: United States | J7: Los Angeles | K7: California | L7: 90032 | M7: West | N7: FUR-FU-10001487 | O7: Furniture | P7: Furnishings | Q7: Eldon Expressions Wood and Plastic Desk Accessories, Cherry Wood | R7: 48.86 | S7: 7 | T7: 0 | U7: 14.1694 | V7: =IF(data[[#This Row],[Sales]]>500,"High","Low") -> Low | W7: =NOW() -> 46152.637 | X7: =DATEDIF(data[[#This Row],[Order Date]], data[[#This Row],[Ship Date]], "d") -> 5 | Y7: =YEAR(TODAY()) -> 2026 | Z7: =EOMONTH(data[[#This Row],[Order Date]],0) -> 41820 | AA7: =LEFT(data[[#This Row],[Customer Name]],3) -> Bro
A8: 7 | B8: CA-2014-115812 | C8: 41799 | D8: 41804 | E8: Standard Class | F8: BH-11710 | G8: Brosina Hoffman | H8: Consumer | I8: United States | J8: Los Angeles | K8: California | L8: 90032 | M8: West | N8: OFF-AR-10002833 | O8: Office Supplies | P8: Art | Q8: Newell 322 | R8: 7.28 | S8: 4 | T8: 0 | U8: 1.9656 | V8: =IF(data[[#This Row],[Sales]]>500,"High","Low") -> Low | W8: =NOW() -> 46152.637 | X8: =DATEDIF(data[[#This Row],[Order Date]], data[[#This Row],[Ship Date]], "d") -> 5 | Y8: =YEAR(TODAY()) -> 2026 | Z8: =EOMONTH(data[[#This Row],[Order Date]],0) -> 41820 | AA8: =LEFT(data[[#This Row],[Customer Name]],3) -> Bro
A9: 8 | B9: CA-2014-115812 | C9: 41799 | D9: 41804 | E9: Standard Class | F9: BH-11710 | G9: Brosina Hoffman | H9: Consumer | I9: United States | J9: Los Angeles | K9: California | L9: 90032 | M9: West | N9: TEC-PH-10002275 | O9: Technology | P9: Phones | Q9: Mitel 5320 IP Phone VoIP phone | R9: 907.152 | S9: 6 | T9: 0.2 | U9: 90.7152 | V9: =IF(data[[#This Row],[Sales]]>500,"High","Low") -> High | W9: =NOW() -> 46152.637 | X9: =DATEDIF(data[[#This Row],[Order Date]], data[[#This Row],[Ship Date]], "d") -> 5 | Y9: =YEAR(TODAY()) -> 2026 | Z9: =EOMONTH(data[[#This Row],[Order Date]],0) -> 41820 | AA9: =LEFT(data[[#This Row],[Customer Name]],3) -> Bro
A10: 9 | B10: CA-2014-115812 | C10: 41799 | D10: 41804 | E10: Standard Class | F10: BH-11710 | G10: Brosina Hoffman | H10: Consumer | I10: United States | J10: Los Angeles | K10: California | L10: 90032 | M10: West | N10: OFF-BI-10003910 | O10: Office Supplies | P10: Binders | Q10: DXL Angle-View Binders with Locking Rings by Samsill | R10: 18.504 | S10: 3 | T10: 0.2 | U10: 5.7825 | V10: =IF(data[[#This Row],[Sales]]>500,"High","Low") -> Low | W10: =NOW() -> 46152.637 | X10: =DATEDIF(data[[#This Row],[Order Date]], data[[#This Row],[Ship Date]], "d") -> 5 | Y10: =YEAR(TODAY()) -> 2026 | Z10: =EOMONTH(data[[#This Row],[Order Date]],0) -> 41820 | AA10: =LEFT(data[[#This Row],[Customer Name]],3) -> Bro
A11: 10 | B11: CA-2014-115812 | C11: 41799 | D11: 41804 | E11: Standard Class | F11: BH-11710 | G11: Brosina Hoffman | H11: Consumer | I11: United States | J11: Los Angeles | K11: California | L11: 90032 | M11: West | N11: OFF-AP-10002892 | O11: Office Supplies | P11: Appliances | Q11: Belkin F5C206VTEL 6 Outlet Surge | R11: 114.9 | S11: 5 | T11: 0 | U11: 34.47 | V11: =IF(data[[#This Row],[Sales]]>500,"High","Low") -> Low | W11: =NOW() -> 46152.637 | X11: =DATEDIF(data[[#This Row],[Order Date]], data[[#This Row],[Ship Date]], "d") -> 5 | Y11: =YEAR(TODAY()) -> 2026 | Z11: =EOMONTH(data[[#This Row],[Order Date]],0) -> 41820 | AA11: =LEFT(data[[#This Row],[Customer Name]],3) -> Bro
A12: 11 | B12: CA-2014-115812 | C12: 41799 | D12: 41804 | E12: Standard Class | F12: BH-11710 | G12: Brosina Hoffman | H12: Consumer | I12: United States | J12: Los Angeles | K12: California | L12: 90032 | M12: West | N12: FUR-TA-10001539 | O12: Furniture | P12: Tables | Q12: Chromcraft Rectangular Conference Tables | R12: 1706.184 | S12: 9 | T12: 0.2 | U12: 85.3092 | V12: =IF(data[[#This Row],[Sales]]>500,"High","Low") -> High | W12: =NOW() -> 46152.637 | X12: =DATEDIF(data[[#This Row],[Order Date]], data[[#This Row],[Ship Date]], "d") -> 5 | Y12: =YEAR(TODAY()) -> 2026 | Z12: =EOMONTH(data[[#This Row],[Order Date]],0) -> 41820 | AA12: =LEFT(data[[#This Row],[Customer Name]],3) -> Bro
A13: 12 | B13: CA-2014-115812 | C13: 41799 | D13: 41804 | E13: Standard Class | F13: BH-11710 | G13: Brosina Hoffman | H13: Consumer | I13: United States | J13: Los Angeles | K13: California | L13: 90032 | M13: West | N13: TEC-PH-10002033 | O13: Technology | P13: Phones | Q13: Konftel 250 Conference phone - Charcoal black | R13: 911.424 | S13: 4 | T13: 0.2 | U13: 68.3568 | V13: =IF(data[[#This Row],[Sales]]>500,"High","Low") -> High | W13: =NOW() -> 46152.637 | X13: =DATEDIF(data[[#This Row],[Order Date]], data[[#This Row],[Ship Date]], "d") -> 5 | Y13: =YEAR(TODAY()) -> 2026 | Z13: =EOMONTH(data[[#This Row],[Order Date]],0) -> 41820 | AA13: =LEFT(data[[#This Row],[Customer Name]],3) -> Bro
... A18: 17 | B18: CA-2014-105893 | C18: 41954 | D18: 41961 | E18: Standard Class | F18: PK-19075 | G18: Pete Kriz | H18: Consumer | I18: United States | J18: Madison | K18: Wisconsin | L18: 53711 | M18: Central | N18: OFF-ST-10004186 | O18: Office Supplies | P18: Storage | Q18: Stur-D-Stor Shelving, Vertical 5-Shelf: 72"H x 36"W x 18 1/2"D | R18: 665.88 | S18: 6 | T18: 0 | U18: 13.3176 | V18: =IF(data[[#This Row],[Sales]]>500,"High","Low") -> High | W18: =NOW() -> 46152.637 | X18: =DATEDIF(data[[#This Row],[Order Date]], data[[#This Row],[Ship Date]], "d") -> 7 | Y18: =YEAR(TODAY()) -> 2026 | Z18: =EOMONTH(data[[#This Row],[Order Date]],0) -> 41973 | AA18: =LEFT(data[[#This Row],[Customer Name]],3) -> Pet
A19: 18 | B19: 46152 | C19: 41772 | D19: 41774 | E19: Second Class | F19: AG-10270 | G19: Alejandro Grove | H19: Consumer | I19: United States | J19: West Jordan | K19: Utah | L19: 84084 | M19: West | N19: OFF-ST-10000107 | O19: Office Supplies | P19: Storage | Q19: Fellowes Super Stor/Drawer | R19: 55.5 | S19: 2 | T19: 0 | U19: 9.99 | V19: =IF(data[[#This Row],[Sales]]>500,"High","Low") -> Low | W19: =NOW() -> 46152.637 | X19: =DATEDIF(data[[#This Row],[Order Date]], data[[#This Row],[Ship Date]], "d") -> 2 | Y19: =YEAR(TODAY()) -> 2026 | Z19: =EOMONTH(data[[#This Row],[Order Date]],0) -> 41790 | AA19: =LEFT(data[[#This Row],[Customer Name]],3) -> Ale
A20: 19 | B20: CA-2014-143336 | C20: 41878 | D20: 41883 | E20: Second Class | F20: ZD-21925 | G20: Zuschuss Donatelli | H20: Consumer | I20: United States | J20: San Francisco | K20: California | L20: 94109 | M20: West | N20: OFF-AR-10003056 | O20: Office Supplies | P20: Art | Q20: Newell 341 | R20: 8.56 | S20: 2 | T20: 0 | U20: 2.4824 | V20: =IF(data[[#This Row],[Sales]]>500,"High","Low") -> Low | W20: =NOW() -> 46152.637 | X20: =DATEDIF(data[[#This Row],[Order Date]], data[[#This Row],[Ship Date]], "d") -> 5 | Y20: =YEAR(TODAY()) -> 2026 | Z20: =EOMONTH(data[[#This Row],[Order Date]],0) -> 41882 | AA20: =LEFT(data[[#This Row],[Customer Name]],3) -> Zus
A21: 20 | B21: CA-2014-143336 | C21: 41878 | D21: 41883 | E21: Second Class | F21: ZD-21925 | G21: Zuschuss Donatelli | H21: Consumer | I21: United States | J21: San Francisco | K21: California | L21: 94109 | M21: West | N21: TEC-PH-10001949 | O21: Technology | P21: Phones | Q21: Cisco SPA 501G IP Phone | R21: 213.48 | S21: 3 | T21: 0.2 | U21: 16.011 | V21: =IF(data[[#This Row],[Sales]]>500,"High","Low") -> Low | W21: =NOW() -> 46152.637 | X21: =DATEDIF(data[[#This Row],[Order Date]], data[[#This Row],[Ship Date]], "d") -> 5 | Y21: =YEAR(TODAY()) -> 2026 | Z21: =EOMONTH(data[[#This Row],[Order Date]],0) -> 41882 | AA21: =LEFT(data[[#This Row],[Customer Name]],3) -> Zus
A22: 21 | B22: CA-2014-143336 | C22: 41878 | D22: 41883 | E22: Second Class | F22: ZD-21925 | G22: Zuschuss Donatelli | H22: Consumer | I22: United States | J22: San Francisco | K22: California | L22: 94109 | M22: West | N22: OFF-BI-10002215 | O22: Office Supplies | P22: Binders | Q22: Wilson Jones Hanging View Binder, White, 1" | R22: 22.72 | S22: 4 | T22: 0.2 | U22: 7.384 | V22: =IF(data[[#This Row],[Sales]]>500,"High","Low") -> Low | W22: =NOW() -> 46152.637 | X22: =DATEDIF(data[[#This Row],[Order Date]], data[[#This Row],[Ship Date]], "d") -> 5 | Y22: =YEAR(TODAY()) -> 2026 | Z22: =EOMONTH(data[[#This Row],[Order Date]],0) -> 41882 | AA22: =LEFT(data[[#This Row],[Customer Name]],3) -> Zus
A23: 22 | B23: CA-2016-137330 | C23: 42713 | D23: 42717 | E23: Standard Class | F23: KB-16585 | G23: Ken Black | H23: Corporate | I23: United States | J23: Fremont | K23: Nebraska | L23: 68025 | M23: Central | N23: OFF-AR-10000246 | O23: Office Supplies | P23: Art | Q23: Newell 318 | R23: 19.46 | S23: 7 | T23: 0 | U23: 5.0596 | V23: =IF(data[[#This Row],[Sales]]>500,"High","Low") -> Low | W23: =NOW() -> 46152.637 | X23: =DATEDIF(data[[#This Row],[Order Date]], data[[#This Row],[Ship Date]], "d") -> 4 | Y23: =YEAR(TODAY()) -> 2026 | Z23: =EOMONTH(data[[#This Row],[Order Date]],0) -> 42735 | AA23: =LEFT(data[[#This Row],[Customer Name]],3) -> Ken
A24: 23 | B24: CA-2016-137330 | C24: 42713 | D24: 42717 | E24: Standard Class | F24: KB-16585 | G24: Ken Black | H24: Corporate | I24: United States | J24: Fremont | K24: Nebraska | L24: 68025 | M24: Central | N24: OFF-AP-10001492 | O24: Office Supplies | P24: Appliances | Q24: Acco Six-Outlet Power Strip, 4' Cord Length | R24: 60.34 | S24: 7 | T24: 0 | U24: 15.6884 | V24: =IF(data[[#This Row],[Sales]]>500,"High","Low") -> Low | W24: =NOW() -> 46152.637 | X24: =DATEDIF(data[[#This Row],[Order Date]], data[[#This Row],[Ship Date]], "d") -> 4 | Y24: =YEAR(TODAY()) -> 2026 | Z24: =EOMONTH(data[[#This Row],[Order Date]],0) -> 42735 | AA24: =LEFT(data[[#This Row],[Customer Name]],3) -> Ken
A25: 24 | B25: US-2017-156909 | C25: 42932 | D25: 42934 | E25: Second Class | F25: SF-20065 | G25: Sandra Flanagan | H25: Consumer | I25: United States | J25: Philadelphia | K25: Pennsylvania | L25: 19140 | M25: East | N25: FUR-CH-10002774 | O25: Furniture | P25: Chairs | Q25: Global Deluxe Stacking Chair, Gray | R25: 71.372 | S25: 2 | T25: 0.3 | U25: -1.0196 | V25: =IF(data[[#This Row],[Sales]]>500,"High","Low") -> Low | W25: =NOW() -> 46152.637 | X25: =DATEDIF(data[[#This Row],[Order Date]], data[[#This Row],[Ship Date]], "d") -> 2 | Y25: =YEAR(TODAY()) -> 2026 | Z25: =EOMONTH(data[[#This Row],[Order Date]],0) -> 42947 | AA25: =LEFT(data[[#This Row],[Customer Name]],3) -> San
A26: 25 | B26: CA-2015-106320 | C26: 42272 | D26: 42277 | E26: Standard Class | F26: EB-13870 | G26: Emily Burns | H26: Consumer | I26: United States | J26: Orem | K26: Utah | L26: 84057 | M26: West | N26: FUR-TA-10000577 | O26: Furniture | P26: Tables | Q26: Bretford CR4500 Series Slim Rectangular Table | R26: 1044.63 | S26: 3 | T26: 0 | U26: 240.2649 | V26: =IF(data[[#This Row],[Sales]]>500,"High","Low") -> High | W26: =NOW() -> 46152.637 | X26: =DATEDIF(data[[#This Row],[Order Date]], data[[#This Row],[Ship Date]], "d") -> 5 | Y26: =YEAR(TODAY()) -> 2026 | Z26: =EOMONTH(data[[#This Row],[Order Date]],0) -> 42277 | AA26: =LEFT(data[[#This Row],[Customer Name]],3) -> Emi
A27: 26 | B27: CA-2016-121755 | C27: 42385 | D27: 42389 | E27: Second Class | F27: EH-13945 | G27: Eric Hoffmann | H27: Consumer | I27: United States | J27: Los Angeles | K27: California | L27: 90049 | M27: West | N27: OFF-BI-10001634 | O27: Office Supplies | P27: Binders | Q27: Wilson Jones Active Use Binders | R27: 11.648 | S27: 2 | T27: 0.2 | U27: 4.2224 | V27: =IF(data[[#This Row],[Sales]]>500,"High","Low") -> Low | W27: =NOW() -> 46152.637 | X27: =DATEDIF(data[[#This Row],[Order Date]], data[[#This Row],[Ship Date]], "d") -> 4 | Y27: =YEAR(TODAY()) -> 2026 | Z27: =EOMONTH(data[[#This Row],[Order Date]],0) -> 42400 | AA27: =LEFT(data[[#This Row],[Customer Name]],3) -> Eri
A28: 27 | B28: CA-2016-121755 | C28: 42385 | D28: 42389 | E28: Second Class | F28: EH-13945 | G28: Eric Hoffmann | H28: Consumer | I28: United States | J28: Los Angeles | K28: California | L28: 90049 | M28: West | N28: TEC-AC-10003027 | O28: Technology | P28: Accessories | Q28: Imation 8GB Mini TravelDrive USB 2.0 Flash Drive | R28: 90.57 | S28: 3 | T28: 0 | U28: 11.7741 | V28: =IF(data[[#This Row],[Sales]]>500,"High","Low") -> Low | W28: =NOW() -> 46152.637 | X28: =DATEDIF(data[[#This Row],[Order Date]], data[[#This Row],[Ship Date]], "d") -> 4 | Y28: =YEAR(TODAY()) -> 2026 | Z28: =EOMONTH(data[[#This Row],[Order Date]],0) -> 42400 | AA28: =LEFT(data[[#This Row],[Customer Name]],3) -> Eri
A29: 28 | B29: US-2015-150630 | C29: 42264 | D29: 42268 | E29: Standard Class | F29: TB-21520 | G29: Tracy Blumstein | H29: Consumer | I29: United States | J29: Philadelphia | K29: Pennsylvania | L29: 19140 | M29: East | N29: FUR-BO-10004834 | O29: Furniture | P29: Bookcases | Q29: Riverside Palais Royal Lawyers Bookcase, Royale Cherry Finish | R29: 3083.43 | S29: 7 | T29: 0.5 | U29: -1665.0522 | V29: =IF(data[[#This Row],[Sales]]>500,"High","Low") -> High | W29: =NOW() -> 46152.637 | X29: =DATEDIF(data[[#This Row],[Order Date]], data[[#This Row],[Ship Date]], "d") -> 4 | Y29: =YEAR(TODAY()) -> 2026 | Z29: =EOMONTH(data[[#This Row],[Order Date]],0) -> 42277 | AA29: =LEFT(data[[#This Row],[Customer Name]],3) -> Tra
A30: 29 | B30: US-2015-150630 | C30: 42264 | D30: 42268 | E30: Standard Class | F30: TB-21520 | G30: Tracy Blumstein | H30: Consumer | I30: United States | J30: Philadelphia | K30: Pennsylvania | L30: 19140 | M30: East | N30: OFF-BI-10000474 | O30: Office Supplies | P30: Binders | Q30: Avery Recycled Flexi-View Covers for Binding Systems | R30: 9.618 | S30: 2 | T30: 0.7 | U30: -7.0532 | V30: =IF(data[[#This Row],[Sales]]>500,"High","Low") -> Low | W30: =NOW() -> 46152.637 | X30: =DATEDIF(data[[#This Row],[Order Date]], data[[#This Row],[Ship Date]], "d") -> 4 | Y30: =YEAR(TODAY()) -> 2026 | Z30: =EOMONTH(data[[#This Row],[Order Date]],0) -> 42277 | AA30: =LEFT(data[[#This Row],[Customer Name]],3) -> Tra
A31: 30 | B31: US-2015-150630 | C31: 42264 | D31: 42268 | E31: Standard Class | F31: TB-21520 | G31: Tracy Blumstein | H31: Consumer | I31: United States | J31: Philadelphia | K31: Pennsylvania | L31: 19140 | M31: East | N31: FUR-FU-10004848 | O31: Furniture | P31: Furnishings | Q31: Howard Miller 13-3/4" Diameter Brushed Chrome Round Wall Clock | R31: 124.2 | S31: 3 | T31: 0.2 | U31: 15.525 | V31: =IF(data[[#This Row],[Sales]]>500,"High","Low") -> Low | W31: =NOW() -> 46152.637 | X31: =DATEDIF(data[[#This Row],[Order Date]], data[[#This Row],[Ship Date]], "d") -> 4 | Y31: =YEAR(TODAY()) -> 2026 | Z31: =EOMONTH(data[[#This Row],[Order Date]],0) -> 42277 | AA31: =LEFT(data[[#This Row],[Customer Name]],3) -> Tra
... A500: 499 | B500: CA-2016-126158 | C500: 42576 | D500: 42582 | E500: Standard Class | F500: SC-20095 | G500: Sanjit Chand | H500: Consumer | I500: United States | J500: Costa Mesa | K500: California | L500: 92627 | M500: West | N500: FUR-CH-10002602 | O500: Furniture | P500: Chairs | Q500: DMI Arturo Collection Mission-style Design Wood Chair | R500: 241.568 | S500: 2 | T500: 0.2 | U500: 18.1176 | V500: =IF(data[[#This Row],[Sales]]>500,"High","Low") -> Low | W500: =NOW() -> 46152.637 | X500: =DATEDIF(data[[#This Row],[Order Date]], data[[#This Row],[Ship Date]], "d") -> 6 | Y500: =YEAR(TODAY()) -> 2026 | Z500: =EOMONTH(data[[#This Row],[Order Date]],0) -> 42582 | AA500: =LEFT(data[[#This Row],[Customer Name]],3) -> San

Sheet RowData
A1: Row ID | B1: Order ID | C1: Order Date | D1: Ship Date | E1: Ship Mode | F1: Customer ID | G1: Customer Name | H1: Segment | I1: Country | J1: City | K1: State | L1: Postal Code | M1: Region | N1: Product ID | O1: Category | P1: Sub-Category | Q1: Product Name | R1: Sales | S1: Quantity | T1: Discount | U1: Profit
A2: 1 | B2: CA-2016-152156 | C2: 42682 | D2: 42685 | E2: Second Class | F2: CG-12520 | G2: Claire Gute | H2: Consumer | I2: United States | J2: Henderson | K2: Kentucky | L2: 42420 | M2: South | N2: FUR-BO-10001798 | O2: Furniture | P2: Bookcases | Q2: Bush Somerset Collection Bookcase | R2: 261.96 | S2: 2 | T2: 0 | U2: 41.9136
A3: 2 | B3: CA-2016-152156 | C3: 42682 | D3: 42685 | E3: Second Class | F3: CG-12520 | G3: Claire Gute | H3: Consumer | I3: United States | J3: Henderson | K3: Kentucky | L3: 42420 | M3: South | N3: FUR-CH-10000454 | O3: Furniture | P3: Chairs | Q3: Hon Deluxe Fabric Upholstered Stacking Chairs, Rounded Back | R3: 731.94 | S3: 3 | T3: 0 | U3: 219.582
A4: 3 | B4: CA-2016-138688 | C4: 42533 | D4: 42537 | E4: Second Class | F4: DV-13045 | G4: Darrin Van Huff | H4: Corporate | I4: United States | J4: Los Angeles | K4: California | L4: 90036 | M4: West | N4: OFF-LA-10000240 | O4: Office Supplies | P4: Labels | Q4: Self-Adhesive Address Labels for Typewriters by Universal | R4: 14.62 | S4: 2 | T4: 0 | U4: 6.8714
A5: 4 | B5: US-2015-108966 | C5: 42288 | D5: 42295 | E5: Standard Class | F5: SO-20335 | G5: Sean O'Donnell | H5: Consumer | I5: United States | J5: Fort Lauderdale | K5: Florida | L5: 33311 | M5: South | N5: FUR-TA-10000577 | O5: Furniture | P5: Tables | Q5: Bretford CR4500 Series Slim Rectangular Table | R5: 957.5775 | S5: 5 | T5: 0.45 | U5: -383.031
A6: 5 | B6: US-2015-108966 | C6: 42288 | D6: 42295 | E6: Standard Class | F6: SO-20335 | G6: Sean O'Donnell | H6: Consumer | I6: United States | J6: Fort Lauderdale | K6: Florida | L6: 33311 | M6: South | N6: OFF-ST-10000760 | O6: Office Supplies | P6: Storage | Q6: Eldon Fold 'N Roll Cart System | R6: 22.368 | S6: 2 | T6: 0.2 | U6: 2.5164
A7: 6 | B7: CA-2014-115812 | C7: 41799 | D7: 41804 | E7: Standard Class | F7: BH-11710 | G7: Brosina Hoffman | H7: Consumer | I7: United States | J7: Los Angeles | K7: California | L7: 90032 | M7: West | N7: FUR-FU-10001487 | O7: Furniture | P7: Furnishings | Q7: Eldon Expressions Wood and Plastic Desk Accessories, Cherry Wood | R7: 48.86 | S7: 7 | T7: 0 | U7: 14.1694
A8: 7 | B8: CA-2014-115812 | C8: 41799 | D8: 41804 | E8: Standard Class | F8: BH-11710 | G8: Brosina Hoffman | H8: Consumer | I8: United States | J8: Los Angeles | K8: California | L8: 90032 | M8: West | N8: OFF-AR-10002833 | O8: Office Supplies | P8: Art | Q8: Newell 322 | R8: 7.28 | S8: 4 | T8: 0 | U8: 1.9656
A9: 8 | B9: CA-2014-115812 | C9: 41799 | D9: 41804 | E9: Standard Class | F9: BH-11710 | G9: Brosina Hoffman | H9: Consumer | I9: United States | J9: Los Angeles | K9: California | L9: 90032 | M9: West | N9: TEC-PH-10002275 | O9: Technology | P9: Phones | Q9: Mitel 5320 IP Phone VoIP phone | R9: 907.152 | S9: 6 | T9: 0.2 | U9: 90.7152
A10: 9 | B10: CA-2014-115812 | C10: 41799 | D10: 41804 | E10: Standard Class | F10: BH-11710 | G10: Brosina Hoffman | H10: Consumer | I10: United States | J10: Los Angeles | K10: California | L10: 90032 | M10: West | N10: OFF-BI-10003910 | O10: Office Supplies | P10: Binders | Q10: DXL Angle-View Binders with Locking Rings by Samsill | R10: 18.504 | S10: 3 | T10: 0.2 | U10: 5.7825
A11: 10 | B11: CA-2014-115812 | C11: 41799 | D11: 41804 | E11: Standard Class | F11: BH-11710 | G11: Brosina Hoffman | H11: Consumer | I11: United States | J11: Los Angeles | K11: California | L11: 90032 | M11: West | N11: OFF-AP-10002892 | O11: Office Supplies | P11: Appliances | Q11: Belkin F5C206VTEL 6 Outlet Surge | R11: 114.9 | S11: 5 | T11: 0 | U11: 34.47
A12: 11 | B12: CA-2014-115812 | C12: 41799 | D12: 41804 | E12: Standard Class | F12: BH-11710 | G12: Brosina Hoffman | H12: Consumer | I12: United States | J12: Los Angeles | K12: California | L12: 90032 | M12: West | N12: FUR-TA-10001539 | O12: Furniture | P12: Tables | Q12: Chromcraft Rectangular Conference Tables | R12: 1706.184 | S12: 9 | T12: 0.2 | U12: 85.3092
A13: 12 | B13: CA-2014-115812 | C13: 41799 | D13: 41804 | E13: Standard Class | F13: BH-11710 | G13: Brosina Hoffman | H13: Consumer | I13: United States | J13: Los Angeles | K13: California | L13: 90032 | M13: West | N13: TEC-PH-10002033 | O13: Technology | P13: Phones | Q13: Konftel 250 Conference phone - Charcoal black | R13: 911.424 | S13: 4 | T13: 0.2 | U13: 68.3568
... A500: 499 | B500: CA-2016-126158 | C500: 42576 | D500: 42582 | E500: Standard Class | F500: SC-20095 | G500: Sanjit Chand | H500: Consumer | I500: United States | J500: Costa Mesa | K500: California | L500: 92627 | M500: West | N500: FUR-CH-10002602 | O500: Furniture | P500: Chairs | Q500: DMI Arturo Collection Mission-style Design Wood Chair | R500: 241.568 | S500: 2 | T500: 0.2 | U500: 18.1176
